dnd_character/SRD.py
dnd_character/__init__.py
dnd_character/__main__.py
dnd_character/character.py
dnd_character/classes.py
dnd_character/dice.py
dnd_character/equipment.py
dnd_character/experience.py
dnd_character/monsters.py
dnd_character/roll.py
dnd_character/spellcasting.py
dnd_character/json_cache/OGLv1.0a.txt
dnd_character/json_cache/README.md
dnd_character/json_cache/api_.json
dnd_character/json_cache/api_classes.json
dnd_character/json_cache/api_classes_barbarian.json
dnd_character/json_cache/api_classes_barbarian_levels.json
dnd_character/json_cache/api_classes_bard.json
dnd_character/json_cache/api_classes_bard_levels.json
dnd_character/json_cache/api_classes_cleric.json
dnd_character/json_cache/api_classes_cleric_levels.json
dnd_character/json_cache/api_classes_druid.json
dnd_character/json_cache/api_classes_druid_levels.json
dnd_character/json_cache/api_classes_fighter.json
dnd_character/json_cache/api_classes_fighter_levels.json
dnd_character/json_cache/api_classes_monk.json
dnd_character/json_cache/api_classes_monk_levels.json
dnd_character/json_cache/api_classes_paladin.json
dnd_character/json_cache/api_classes_paladin_levels.json
dnd_character/json_cache/api_classes_ranger.json
dnd_character/json_cache/api_classes_ranger_levels.json
dnd_character/json_cache/api_classes_rogue.json
dnd_character/json_cache/api_classes_rogue_levels.json
dnd_character/json_cache/api_classes_sorcerer.json
dnd_character/json_cache/api_classes_sorcerer_levels.json
dnd_character/json_cache/api_classes_warlock.json
dnd_character/json_cache/api_classes_warlock_levels.json
dnd_character/json_cache/api_classes_wizard.json
dnd_character/json_cache/api_classes_wizard_levels.json
dnd_character/json_cache/api_equipment-categories_arcane-foci.json
dnd_character/json_cache/api_equipment-categories_druidic-foci.json
dnd_character/json_cache/api_equipment-categories_holy-symbols.json
dnd_character/json_cache/api_equipment-categories_martial-melee-weapons.json
dnd_character-23.7.29.dist-info/LICENSE
dnd_character-23.7.29.dist-info/METADATA
dnd_character-23.7.29.dist-info/WHEEL
dnd_character-23.7.29.dist-info/top_level.txt
dnd_character-23.7.29.dist-info/RECORD
