Metadata-Version: 2.1
Name: dnd-character
Version: 23.7.29
Summary: make Dungeons & Dragons characters as serializable objects
Home-page: https://github.com/tassaron/dnd-character
Author: Brianna Rainey
License: EPL-2.0
Keywords: dnd trpg tabletop rpg
Platform: UNKNOWN
Classifier: Development Status :: 3 - Alpha
Classifier: Intended Audience :: Developers
Classifier: Topic :: Games/Entertainment
Classifier: Topic :: Games/Entertainment :: Role-Playing
Classifier: Programming Language :: Python :: 3.10
Classifier: License :: OSI Approved :: Eclipse Public License 2.0 (EPL-2.0)
License-File: LICENSE
